[{"__type__":"cc.SpriteFrame","content":{"name":"theme","texture":"e9vO9EaShODan5rFYJGpZb","rect":[1,1,1042,1052],"offset":[1,-5],"originalSize":[1080,1112]}},{"__type__":"cc.SpriteFrame","content":{"name":"bg","texture":"f4/rzHg61BmLfdE85NMSrV","rect":[0,0,1080,1920],"offset":[0,0],"originalSize":[1080,1920]}},[{"__type__":"cc.SceneAsset","_name":"login_scene","scene":{"__id__":1},"asyncLoadAssets":null},{"__type__":"cc.Scene","_name":"New Node","_children":[{"__id__":2}],"_anchorPoint":{"__type__":"cc.Vec2"},"autoReleaseAssets":false},{"__type__":"cc.Node","_name":"Canvas","_parent":{"__id__":1},"_children":[{"__id__":3},{"__id__":4},{"__id__":5},{"__id__":8},{"__id__":10},{"__id__":12}],"_components":[{"__type__":"cc.Canvas","node":{"__id__":2},"_designResolution":{"__type__":"cc.Size","width":640,"height":1136},"_fitWidth":true,"_fitHeight":false},{"__type__":"53ec4NBwLtMQoI2otngzQN8","node":{"__id__":2}}],"_id":"c9wu4kGkFJk75xe2NIBxSi","_contentSize":{"__type__":"cc.Size","width":640,"height":1136},"_position":{"__type__":"cc.Vec2","x":320,"y":568}},{"__type__":"cc.Node","_name":"bg_img","_parent":{"__id__":2},"_components":[{"__type__":"cc.Sprite","node":{"__id__":3},"_spriteFrame":{"__uuid__":"3fstzjpJlDeajiryB15sEl"},"_sizeMode":0},{"__type__":"cc.Widget","node":{"__id__":3},"_alignFlags":18}],"_contentSize":{"__type__":"cc.Size","width":640,"height":1600}},{"__type__":"cc.Node","_name":"theme_img","_parent":{"__id__":2},"_components":[{"__type__":"cc.Sprite","node":{"__id__":4},"_spriteFrame":{"__uuid__":"2dNhmcUnREVbR02OkU1rT5"},"_sizeMode":0},{"__type__":"cc.Widget","node":{"__id__":4},"_alignFlags":18,"_top":-545.65,"_verticalCenter":303}],"_contentSize":{"__type__":"cc.Size","width":540,"height":550},"_position":{"__type__":"cc.Vec2","y":303}},{"__type__":"cc.Node","_name":"floor_img","_parent":{"__id__":2},"_children":[{"__id__":6},{"__id__":7}],"_components":[{"__type__":"cc.Sprite","node":{"__id__":5},"_spriteFrame":{"__uuid__":"facQjTfZFLopgzdiggAKhf"},"_sizeMode":0},{"__type__":"cc.Widget","node":{"__id__":5},"_alignFlags":4}],"_contentSize":{"__type__":"cc.Size","width":640,"height":432},"_position":{"__type__":"cc.Vec2","y":-352}},{"__type__":"cc.Node","_name":"man_img","_parent":{"__id__":5},"_active":false,"_components":[{"__type__":"cc.Sprite","node":{"__id__":6},"_spriteFrame":{"__uuid__":"d9EyrlnP9Hy5jVQ3FMooWz"},"_sizeMode":0},{"__type__":"cc.Widget","node":{"__id__":6},"_alignFlags":20,"_bottom":400.65,"_horizontalCenter":4}],"_contentSize":{"__type__":"cc.Size","width":211,"height":234.7},"_position":{"__type__":"cc.Vec2","x":4,"y":302}},{"__type__":"cc.Node","_name":"woman_img","_parent":{"__id__":5},"_components":[{"__type__":"cc.Sprite","node":{"__id__":7},"_spriteFrame":{"__uuid__":"67MmBNz6VD8ZzoQ0kcO+Sh"},"_sizeMode":0},{"__type__":"cc.Widget","node":{"__id__":7},"_alignFlags":20,"_bottom":400.65,"_horizontalCenter":4}],"_contentSize":{"__type__":"cc.Size","width":211,"height":234.7},"_position":{"__type__":"cc.Vec2","x":4,"y":302}},{"__type__":"cc.Node","_name":"rnak_btn","_parent":{"__id__":2},"_children":[{"__id__":9}],"_components":[{"__type__":"cc.Sprite","node":{"__id__":8},"_spriteFrame":{"__uuid__":"92eZSLTQpKB7oJMIvb0yFo"},"_sizeMode":0},{"__type__":"cc.Widget","node":{"__id__":8},"_alignFlags":12,"_left":134.5,"_right":429.5,"_top":798,"_bottom":104,"_originalWidth":101,"_originalHeight":100},{"__type__":"cc.Button","node":{"__id__":8},"transition":1,"pressedColor":{"__type__":"cc.Color","r":201,"g":201,"b":201},"hoverColor":{"__type__":"cc.Color","r":201,"g":196,"b":196},"clickEvents":[{"__type__":"cc.ClickEvent","target":{"__id__":2},"component":"login","handler":"rankBtnAction"}],"_N$normalColor":{"__type__":"cc.Color","r":255,"g":255,"b":255},"_N$disabledColor":{"__type__":"cc.Color","r":117,"g":117,"b":117},"_N$target":{"__id__":8}}],"_contentSize":{"__type__":"cc.Size","width":101,"height":100},"_position":{"__type__":"cc.Vec2","x":-135,"y":-414}},{"__type__":"cc.Node","_name":"rank_font","_parent":{"__id__":8},"_components":[{"__type__":"cc.Label","node":{"__id__":9},"_useOriginalSize":false,"_actualFontSize":35,"_fontSize":35,"_N$string":"查看\n排行","_N$horizontalAlign":1,"_N$verticalAlign":1},{"__type__":"cc.Widget","node":{"__id__":9},"_alignFlags":12,"_left":-83.5,"_right":545,"_bottom":10,"_originalWidth":70},{"__type__":"cc.LabelOutline","node":{"__id__":9},"_color":{"__type__":"cc.Color","r":131,"g":130,"b":129},"_width":0.5}],"_color":{"__type__":"cc.Color","r":131,"g":130,"b":129},"_contentSize":{"__type__":"cc.Size","width":71,"height":80},"_position":{"__type__":"cc.Vec2","x":-98.5}},{"__type__":"cc.Node","_name":"award_btn","_parent":{"__id__":2},"_children":[{"__id__":11}],"_components":[{"__type__":"cc.Sprite","node":{"__id__":10},"_spriteFrame":{"__uuid__":"d04+KRW1NFro7iG1mqoRcI"},"_sizeMode":0},{"__type__":"cc.Widget","node":{"__id__":10},"_alignFlags":36,"_left":429.5,"_right":133.5,"_top":798,"_bottom":104,"_originalWidth":101,"_originalHeight":100},{"__type__":"cc.Button","node":{"__id__":10},"transition":1,"pressedColor":{"__type__":"cc.Color","r":201,"g":201,"b":201},"hoverColor":{"__type__":"cc.Color","r":201,"g":196,"b":196},"clickEvents":[{"__type__":"cc.ClickEvent","target":{"__id__":2},"component":"login","handler":"awardBtnAction"}],"_N$normalColor":{"__type__":"cc.Color","r":255,"g":255,"b":255},"_N$disabledColor":{"__type__":"cc.Color","r":117,"g":117,"b":117},"_N$target":{"__id__":10}}],"_contentSize":{"__type__":"cc.Size","width":101,"height":100},"_position":{"__type__":"cc.Vec2","x":136,"y":-414}},{"__type__":"cc.Node","_name":"award_font","_parent":{"__id__":10},"_components":[{"__type__":"cc.Label","node":{"__id__":11},"_useOriginalSize":false,"_actualFontSize":35,"_fontSize":35,"_N$string":"我的\n奖励","_N$horizontalAlign":1,"_N$verticalAlign":1},{"__type__":"cc.Widget","node":{"__id__":11},"_alignFlags":36,"_left":545,"_right":-83.5,"_bottom":10,"_originalWidth":70},{"__type__":"cc.LabelOutline","node":{"__id__":11},"_color":{"__type__":"cc.Color","r":131,"g":130,"b":129},"_width":0.5}],"_color":{"__type__":"cc.Color","r":131,"g":130,"b":129},"_contentSize":{"__type__":"cc.Size","width":71,"height":80},"_position":{"__type__":"cc.Vec2","x":98.5}},{"__type__":"cc.Node","_name":"start_btn","_parent":{"__id__":2},"_components":[{"__type__":"cc.Sprite","node":{"__id__":12},"_spriteFrame":{"__uuid__":"9aO6OYSKdKbZh9wyHU7PsR"},"_sizeMode":0},{"__type__":"cc.Widget","node":{"__id__":12},"_alignFlags":20,"_left":109.5,"_right":109.5,"_bottom":249,"_originalWidth":421},{"__type__":"cc.Button","node":{"__id__":12},"transition":1,"pressedColor":{"__type__":"cc.Color","r":201,"g":201,"b":201},"hoverColor":{"__type__":"cc.Color","r":201,"g":196,"b":196},"clickEvents":[{"__type__":"cc.ClickEvent","target":{"__id__":2},"component":"login","handler":"startBtnAction"}],"_N$normalColor":{"__type__":"cc.Color","r":255,"g":255,"b":255},"_N$disabledColor":{"__type__":"cc.Color","r":117,"g":117,"b":117},"_N$target":{"__id__":12}}],"_contentSize":{"__type__":"cc.Size","width":371,"height":100},"_position":{"__type__":"cc.Vec2","y":-269}}],{"__type__":"cc.SpriteFrame","content":{"name":"woman","texture":"e9vO9EaShODan5rFYJGpZb","rect":[1,1055,263,302],"offset":[0,0],"originalSize":[263,302],"rotated":1}},{"__type__":"cc.SpriteFrame","content":{"name":"rankbtn","texture":"d4WUIV025K3449vFYDZQYh","rect":[749,154,151,150],"offset":[0,0],"originalSize":[151,150],"rotated":1}},{"__type__":"cc.SpriteFrame","content":{"name":"startbtn","texture":"d4WUIV025K3449vFYDZQYh","rect":[1,351,571,173],"offset":[0,0],"originalSize":[571,173]}},{"__type__":"cc.SpriteFrame","content":{"name":"award","texture":"d4WUIV025K3449vFYDZQYh","rect":[749,1,151,150],"offset":[0,0],"originalSize":[151,150],"rotated":1}},{"__type__":"cc.SpriteFrame","content":{"name":"man","texture":"e9vO9EaShODan5rFYJGpZb","rect":[305,1055,261,295],"offset":[0,0],"originalSize":[261,295],"rotated":1}},{"__type__":"cc.SpriteFrame","content":{"name":"floor","texture":"bc9XXCeIVIsrq4EiShL84Y","rect":[0,625,1080,611],"offset":[0,-312.5],"originalSize":[1080,1236]}}]